solutions/3.busPermutator/busPermutator.v
`timescale 1ns / 1ns

module busPermutator(
    input [3:0] din,
    input [4:0] select,
    output reg [3:0] dout
);

// cases generated by chatGPT on a smaller scale code since I dont think that was the smart solution
// I was trying to look for a way to implement dependancy between switch cases with instant output and no
// clocks but couldnt find the answer

always @(din, select) begin
    case (select)
        // 5'b00000: dout = din;            // No permutation
        // 5'b00001: dout = din[3:0];        // Reverse order
        // 5'b00010: dout = din[2:0] & din[3];// Shift right by 1
        // 5'b00011: dout = din[1:0] & din[3:2]; // Shift right by 2
        5'b00100: dout = {din[0], din[3:1]}; // Swap first and last bits
        5'b00101: dout = {din[0], din[2:1], din[3]}; // Custom permutation 1
        5'b00110: dout = {din[2:0], din[3]}; // Custom permutation 2
        5'b00111: dout = {din[1:0], din[3:2]}; // Custom permutation 3
        5'b01000: dout = {din[1], din[3:2], din[0]}; // Custom permutation 4
        5'b01001: dout = {din[2], din[3], din[1:0]}; // Custom permutation 5
        5'b01010: dout = {din[1], din[0], din[3:2]}; // Custom permutation 6
        5'b01011: dout = {din[0], din[1], din[2], din[3]}; // Permutation 7
        5'b01100: dout = {din[0], din[2:1], din[3]}; // Permutation 8
        5'b01101: dout = {din[3:2], din[1:0]}; // Permutation 9
        5'b01110: dout = {din[2], din[0], din[1], din[3]}; // Permutation 10
        5'b01111: dout = {din[1], din[3], din[2:0]}; // Permutation 11
        5'b10000: dout = {din[3], din[1:0], din[2]}; // Permutation 12
        5'b10001: dout = {din[0], din[3:1], din[2]}; // Permutation 13
        5'b10010: dout = {din[2:1], din[3:0]}; // Permutation 14
        5'b10011: dout = {din[1], din[3:2], din[0]}; // Permutation 15
        5'b10100: dout = {din[3:2], din[0], din[1]}; // Permutation 16
        5'b10101: dout = {din[1:0], din[3], din[2]}; // Permutation 17
        5'b10110: dout = {din[3], din[0], din[2:1]}; // Permutation 18
        5'b10111: dout = {din[2], din[1], din[0], din[3]}; // Permutation 19
        5'b11000: dout = {din[0], din[3:1], din[2]}; // Permutation 20
        5'b11001: dout = {din[2:1], din[0], din[3]}; // Permutation 21
        5'b11010: dout = {din[3], din[1], din[0], din[2]}; // Permutation 22
        5'b11011: dout = {din[0], din[2], din[3], din[1]}; // Permutation 23
        5'b11100: dout = {din[1], din[2], din[3], din[0]}; // Permutation 24
        default: dout = din;               // Default case, no permutation
    endcase
  end

endmodule

solutions/3.busPermutator/tb.v
module testbench;
reg [3:0] din;
reg [4:0] select;
wire [3:0] dout;


always begin
    #10;
    select = $random;
    #10;
    din = $random;
end

initial begin
    $dumpvars(0,testbench);
    din = 0;
    #800 $finish;
end

busPermutator dut (.din(din), .select(select), .dout(dout));
endmodule

solutions/3.busPermutator/dump.vcd
$date
	Mon Jan  8 12:18:40 2024
$end
$version
	Icarus Verilog
$end
$timescale
	1ns
$end
$scope module testbench $end
$var wire 4 ! dout [3:0] $end
$var reg 4 " din [3:0] $end
$var reg 5 # select [4:0] $end
$scope module dut $end
$var wire 4 $ din [3:0] $end
$var wire 5 % select [4:0] $end
$var reg 4 & dout [3:0] $end
$upscope $end
$upscope $end
$enddefinitions $end
$comment Show the parameter values. $end
$dumpall
$end
#0
$dumpvars
b0 &
bx %
b0 $
bx #
b0 "
b0 !
$end
#10000000000
b100 #
b100 %
#20000000000
b1000 !
b1000 &
b1 "
b1 $
#30000000000
b1 !
b1 &
b1001 #
b1001 %
#40000000000
b11 !
b11 &
b11 "
b11 $
#50000000000
b1101 #
b1101 %
#60000000000
b1101 !
b1101 &
b1101 "
b1101 $
#70000000000
b101 #
b101 %
#80000000000
b10 !
b10 &
b10 "
b10 $
#90000000000
b1 #
b1 %
#100000000000
b1101 !
b1101 &
b1101 "
b1101 $
#110000000000
b1110 !
b1110 &
b10110 #
b10110 %
#130000000000
b1101 !
b1101 &
b1101 #
b1101 %
#140000000000
b1100 !
b1100 &
b1100 "
b1100 $
#150000000000
b1001 !
b1001 &
b11001 #
b11001 %
#160000000000
b1100 !
b1100 &
b110 "
b110 $
#170000000000
b110 !
b110 &
b101 #
b101 %
#180000000000
b11 !
b11 &
b1010 "
b1010 $
#200000000000
b1110 !
b1110 &
b111 "
b111 $
#210000000000
b111 !
b111 &
b10010 #
b10010 %
#220000000000
b1111 !
b1111 &
b1111 "
b1111 $
#240000000000
b1110 !
b1110 &
b1110 "
b1110 $
#250000000000
b1000 #
b1000 %
#260000000000
b11 !
b11 &
b101 "
b101 $
#270000000000
b101 !
b101 &
b11100 #
b11100 %
#280000000000
b111 !
b111 &
b1101 "
b1101 $
#290000000000
b1101 !
b1101 &
b1101 #
b1101 %
#300000000000
b101 !
b101 &
b101 "
b101 $
#310000000000
b11 #
b11 %
#320000000000
b1010 !
b1010 &
b1010 "
b1010 $
#330000000000
b0 #
b0 %
#340000000000
b0 !
b0 &
b0 "
b0 $
#350000000000
b1010 #
b1010 %
#360000000000
b111 !
b111 &
b1101 "
b1101 $
#370000000000
b1110 !
b1110 &
b10110 #
b10110 %
#380000000000
b101 !
b101 &
b11 "
b11 $
#390000000000
b11 !
b11 &
b1101 #
b1101 %
#410000000000
b1100 !
b1100 &
b1011 #
b1011 %
#420000000000
b1010 !
b1010 &
b101 "
b101 $
#430000000000
b101 !
b101 &
b10 #
b10 %
#440000000000
b1110 !
b1110 &
b1110 "
b1110 $
#450000000000
b11101 #
b11101 %
#460000000000
b1111 !
b1111 &
b1111 "
b1111 $
#470000000000
b11 #
b11 %
#480000000000
b1010 !
b1010 &
b1010 "
b1010 $
#490000000000
b1010 #
b1010 %
#500000000000
b11 !
b11 &
b1100 "
b1100 $
#510000000000
b1100 !
b1100 &
b10010 #
b10010 %
#520000000000
b1010 !
b1010 &
b1010 "
b1010 $
#530000000000
b1 #
b1 %
#540000000000
b1000 !
b1000 &
b1000 "
b1000 $
#550000000000
b11000 #
b11000 %
#560000000000
b1001 "
b1001 $
#570000000000
b1001 !
b1001 &
b1011 #
b1011 %
#580000000000
b110 !
b110 &
b110 "
b110 $
#590000000000
b1100 !
b1100 &
b110 #
b110 %
#600000000000
b1101 !
b1101 &
b1110 "
b1110 $
#610000000000
b1110 !
b1110 &
b11100 #
b11100 %
#620000000000
b1010 !
b1010 &
b1010 "
b1010 $
#630000000000
b101 !
b101 &
b1011 #
b1011 %
#640000000000
b1000 !
b1000 &
b1 "
b1 $
#650000000000
b101 #
b101 %
#660000000000
b1111 !
b1111 &
b1111 "
b1111 $
#670000000000
b11011 #
b11011 %
#680000000000
b11 !
b11 &
b1010 "
b1010 $
#690000000000
b1010 !
b1010 &
b11110 #
b11110 %
#700000000000
b101 !
b101 &
b101 "
b101 $
#710000000000
b10001 #
b10001 %
#720000000000
b1000 !
b1000 &
b1001 "
b1001 $
#730000000000
b1001 !
b1001 &
b10 #
b10 %
#740000000000
b1100 !
b1100 &
b1100 "
b1100 $
#750000000000
b11111 #
b11111 %
#760000000000
b1111 !
b1111 &
b1111 "
b1111 $
#770000000000
b11000 #
b11000 %
#780000000000
b111 !
b111 &
b111 "
b111 $
#790000000000
b11111 #
b11111 %
