solutions/4.Parity/parity.v
`timescale 1ns / 1ns

module parity(
    input clk,
    input rst_n,
    input [31:0] din,
    output [31:0] dout,
    output [3:0] parity
);
//Assumption taken, even parity

reg [31:0] dout_reg;
assign dout = dout_reg;
reg [3:0] parity_reg;
assign parity = parity_reg;

wire [7:0] Q0 = din[7:0];
wire [7:0] Q1 = din[15:8];
wire [7:0] Q2 = din[23:16];
wire [7:0] Q3 = din[31:24];
integer onesQ0;
integer onesQ1;
integer onesQ2;
integer onesQ3;
integer i;


always @(posedge clk) begin
  if (!rst_n) begin
    dout_reg <= 0;
    parity_reg <= 0;
  end
  else begin
    dout_reg <= din;
    onesQ0 = 0;
    onesQ1 = 0;
    onesQ2 = 0;
    onesQ3 = 0;
    for (i=0; i<8; i++) begin
        onesQ0 = onesQ0 + Q0[i];
        onesQ1 = onesQ1 + Q1[i];
        onesQ2 = onesQ2 + Q2[i];
        onesQ3 = onesQ3 + Q3[i];
    end
    parity_reg[0] = onesQ0%2;
    parity_reg[1] = onesQ1%2;
    parity_reg[2] = onesQ2%2;
    parity_reg[3] = onesQ3%2;
  end
end

endmodule

solutions/4.Parity/tb.v
//`include "parity.v"

module testbench;

    reg clk;
    reg rst_n;
    reg [31:0] din;
    wire [31:0] dout;
    wire [3:0] parity;

parity dut (.clk(clk), .rst_n(rst_n), .din(din), .dout(dout), .parity(parity));

always begin
    clk = 0;
    #10;
    clk = 1;
    #5;
    din = $random;
    #5;
end

initial begin
  $dumpvars(0,testbench);
  rst_n = 0;
  #100;
  rst_n = 1;
  #800 $finish;
end
endmodule

solutions/4.Parity/dump.vcd
$date
	Tue Jan  2 14:12:29 2024
$end
$version
	Icarus Verilog
$end
$timescale
	1ns
$end
$scope module testbench $end
$var wire 4 ! parity [3:0] $end
$var wire 32 " dout [31:0] $end
$var reg 1 # clk $end
$var reg 32 $ din [31:0] $end
$var reg 1 % rst_n $end
$scope module dut $end
$var wire 1 # clk $end
$var wire 32 & din [31:0] $end
$var wire 32 ' dout [31:0] $end
$var wire 4 ( parity [3:0] $end
$var wire 1 % rst_n $end
$var wire 8 ) Q3 [7:0] $end
$var wire 8 * Q2 [7:0] $end
$var wire 8 + Q1 [7:0] $end
$var wire 8 , Q0 [7:0] $end
$var reg 32 - dout_reg [31:0] $end
$var reg 4 . parity_reg [3:0] $end
$var integer 32 / i [31:0] $end
$var integer 32 0 onesQ0 [31:0] $end
$var integer 32 1 onesQ1 [31:0] $end
$var integer 32 2 onesQ2 [31:0] $end
$var integer 32 3 onesQ3 [31:0] $end
$upscope $end
$upscope $end
$enddefinitions $end
$comment Show the parameter values. $end
$dumpall
$end
#0
$dumpvars
bx 3
bx 2
bx 1
bx 0
bx /
bx .
bx -
bx ,
bx +
bx *
bx )
bx (
bx '
bx &
0%
bx $
0#
bx "
bx !
$end
#10
b0 !
b0 (
b0 .
b0 "
b0 '
b0 -
1#
#15
b100100 ,
b110101 +
b10101 *
b10010 )
b10010000101010011010100100100 $
b10010000101010011010100100100 &
#20
0#
#30
1#
#35
b10000001 ,
b1011110 +
b10001001 *
b11000000 )
b11000000100010010101111010000001 $
b11000000100010010101111010000001 &
#40
0#
#50
1#
#55
b1001 ,
b11010110 +
b10000100 *
b10000100 )
b10000100100001001101011000001001 $
b10000100100001001101011000001001 &
#60
0#
#70
1#
#75
b1100011 ,
b1010110 +
b11110000 *
b10110001 )
b10110001111100000101011001100011 $
b10110001111100000101011001100011 &
#80
0#
#90
1#
#95
b1101 ,
b1111011 +
b10111001 *
b110 )
b110101110010111101100001101 $
b110101110010111101100001101 &
#100
0#
1%
#110
b110101110010111101100001101 "
b110101110010111101100001101 '
b110101110010111101100001101 -
b101 !
b101 (
b101 .
b1000 /
b10 3
b101 2
b110 1
b11 0
1#
#115
b10001101 ,
b10011001 +
b11011111 *
b1000110 )
b1000110110111111001100110001101 $
b1000110110111111001100110001101 &
#120
0#
#130
b1000110110111111001100110001101 "
b1000110110111111001100110001101 '
b1000110110111111001100110001101 -
b1100 !
b1100 (
b1100 .
b1000 /
b11 3
b111 2
b100 1
b100 0
1#
#135
b1100101 ,
b10000100 +
b11000010 *
b10110010 )
b10110010110000101000010001100101 $
b10110010110000101000010001100101 &
#140
0#
#150
b10110010110000101000010001100101 "
b10110010110000101000010001100101 '
b10110010110000101000010001100101 -
b100 !
b100 (
b100 .
b1000 /
b100 3
b11 2
b10 1
b100 0
1#
#155
b10010 ,
b1010010 +
b110111 *
b10001001 )
b10001001001101110101001000010010 $
b10001001001101110101001000010010 &
#160
0#
#170
b10001001001101110101001000010010 "
b10001001001101110101001000010010 '
b10001001001101110101001000010010 -
b1110 !
b1110 (
b1110 .
b1000 /
b11 3
b101 2
b11 1
b10 0
1#
#175
b1 ,
b11100011 +
b11110011 *
b0 )
b111100111110001100000001 $
b111100111110001100000001 &
#180
0#
#190
b111100111110001100000001 "
b111100111110001100000001 '
b111100111110001100000001 -
b11 !
b11 (
b11 .
b1000 /
b0 3
b110 2
b101 1
b1 0
1#
#195
b1101 ,
b11001101 +
b11010111 *
b110 )
b110110101111100110100001101 $
b110110101111100110100001101 &
#200
0#
#210
b110110101111100110100001101 "
b110110101111100110100001101 '
b110110101111100110100001101 -
b10 3
b1000 /
b110 2
b101 1
b11 0
1#
#215
b1110110 ,
b11110001 +
b100011 *
b111011 )
b111011001000111111000101110110 $
b111011001000111111000101110110 &
#220
0#
#230
b111011001000111111000101110110 "
b111011001000111111000101110110 '
b111011001000111111000101110110 -
b1111 !
b1111 (
b1111 .
b1000 /
b101 3
b11 2
b101 1
b101 0
1#
#235
b111101 ,
b11001101 +
b10001101 *
b11110 )
b11110100011011100110100111101 $
b11110100011011100110100111101 &
#240
0#
#250
b11110100011011100110100111101 "
b11110100011011100110100111101 '
b11110100011011100110100111101 -
b11 !
b11 (
b11 .
b1000 /
b100 3
b100 2
b101 1
b101 0
1#
#255
b11101101 ,
b1010111 +
b11010100 *
b1110110 )
b1110110110101000101011111101101 $
b1110110110101000101011111101101 &
#260
0#
#270
b1110110110101000101011111101101 "
b1110110110101000101011111101101 '
b1110110110101000101011111101101 -
b1010 !
b1010 (
b1010 .
b1000 /
b101 3
b100 2
b101 1
b110 0
1#
#275
b10001100 ,
b11110111 +
b101101 *
b1000110 )
b1000110001011011111011110001100 $
b1000110001011011111011110001100 &
#280
0#
#290
b1000110001011011111011110001100 "
b1000110001011011111011110001100 '
b1000110001011011111011110001100 -
b1011 !
b1011 (
b1011 .
b1000 /
b11 3
b100 2
b111 1
b11 0
1#
#295
b11111001 ,
b11101001 +
b11111101 *
b1111100 )
b1111100111111011110100111111001 $
b1111100111111011110100111111001 &
#300
0#
#310
b1111100111111011110100111111001 "
b1111100111111011110100111111001 '
b1111100111111011110100111111001 -
b1110 !
b1110 (
b1110 .
b1000 /
b101 3
b111 2
b101 1
b110 0
1#
#315
b11000110 ,
b100100 +
b110111 *
b11100011 )
b11100011001101110010010011000110 $
b11100011001101110010010011000110 &
#320
0#
#330
b11100011001101110010010011000110 "
b11100011001101110010010011000110 '
b11100011001101110010010011000110 -
b1100 !
b1100 (
b1100 .
b1000 /
b101 3
b101 2
b10 1
b100 0
1#
#335
b11000101 ,
b10000100 +
b11110111 *
b11100010 )
b11100010111101111000010011000101 $
b11100010111101111000010011000101 &
#340
0#
#350
b11100010111101111000010011000101 "
b11100010111101111000010011000101 '
b11100010111101111000010011000101 -
b100 !
b100 (
b100 .
b1000 /
b100 3
b111 2
b10 1
b100 0
1#
#355
b10101010 ,
b11010010 +
b10011 *
b11010101 )
b11010101000100111101001010101010 $
b11010101000100111101001010101010 &
#360
0#
#370
b11010101000100111101001010101010 "
b11010101000100111101001010101010 '
b11010101000100111101001010101010 -
b1100 !
b1100 (
b1100 .
b1000 /
b101 3
b11 2
b100 1
b100 0
1#
#375
b11100101 ,
b11110111 +
b10101111 *
b1110010 )
b1110010101011111111011111100101 $
b1110010101011111111011111100101 &
#380
0#
#390
b1110010101011111111011111100101 "
b1110010101011111111011111100101 '
b1110010101011111111011111100101 -
b11 !
b11 (
b11 .
b1000 /
b100 3
b110 2
b111 1
b101 0
1#
#395
b1110111 ,
b1110010 +
b11010010 *
b10111011 )
b10111011110100100111001001110111 $
b10111011110100100111001001110111 &
#400
0#
#410
b10111011110100100111001001110111 "
b10111011110100100111001001110111 '
b10111011110100100111001001110111 -
b0 !
b0 (
b0 .
b1000 /
b110 3
b100 2
b100 1
b110 0
1#
#415
b10010 ,
b11010110 +
b110010 *
b10001001 )
b10001001001100101101011000010010 $
b10001001001100101101011000010010 &
#420
0#
#430
b10001001001100101101011000010010 "
b10001001001100101101011000010010 '
b10001001001100101101011000010010 -
b1110 !
b1110 (
b1110 .
b1000 /
b11 3
b11 2
b101 1
b10 0
1#
#435
b10001111 ,
b11011011 +
b11101100 *
b1000111 )
b1000111111011001101101110001111 $
b1000111111011001101101110001111 &
#440
0#
#450
b1000111111011001101101110001111 "
b1000111111011001101101110001111 '
b1000111111011001101101110001111 -
b101 !
b101 (
b101 .
b1000 /
b100 3
b101 2
b110 1
b101 0
1#
#455
b11110010 ,
b1101001 +
b110000 *
b1111001 )
b1111001001100000110100111110010 $
b1111001001100000110100111110010 &
#460
0#
#470
b1111001001100000110100111110010 "
b1111001001100000110100111110010 '
b1111001001100000110100111110010 -
b1001 !
b1001 (
b1001 .
b1000 /
b101 3
b10 2
b100 1
b101 0
1#
#475
b11001110 ,
b10010110 +
b1110110 *
b11100111 )
b11100111011101101001011011001110 $
b11100111011101101001011011001110 &
#480
0#
#490
b11100111011101101001011011001110 "
b11100111011101101001011011001110 '
b11100111011101101001011011001110 -
b101 !
b101 (
b101 .
b1000 /
b110 3
b101 2
b100 1
b101 0
1#
#495
b11101000 ,
b1111010 +
b0 *
b11110100 )
b11110100000000000111101011101000 $
b11110100000000000111101011101000 &
#500
0#
#510
b11110100000000000111101011101000 "
b11110100000000000111101011101000 '
b11110100000000000111101011101000 -
b1010 !
b1010 (
b1010 .
b1000 /
b101 3
b0 2
b101 1
b100 0
1#
#515
b11000101 ,
b1001110 +
b11001010 *
b11100010 )
b11100010110010100100111011000101 $
b11100010110010100100111011000101 &
#520
0#
#530
b11100010110010100100111011000101 "
b11100010110010100100111011000101 '
b11100010110010100100111011000101 -
b0 !
b0 (
b0 .
b100 2
b1000 /
b100 3
b100 1
b100 0
1#
#535
b1011100 ,
b1001001 +
b1011000 *
b101110 )
b101110010110000100100101011100 $
b101110010110000100100101011100 &
#540
0#
#550
b101110010110000100100101011100 "
b101110010110000100100101011100 '
b101110010110000100100101011100 -
b110 !
b110 (
b110 .
b1000 /
b100 3
b11 2
b11 1
b100 0
1#
#555
b10111101 ,
b101000 +
b10001110 *
b11011110 )
b11011110100011100010100010111101 $
b11011110100011100010100010111101 &
#560
0#
#570
b11011110100011100010100010111101 "
b11011110100011100010100010111101 '
b11011110100011100010100010111101 -
b0 !
b0 (
b0 .
b1000 /
b110 3
b100 2
b10 1
b110 0
1#
#575
b101101 ,
b1011000 +
b10101011 *
b10010110 )
b10010110101010110101100000101101 $
b10010110101010110101100000101101 &
#580
0#
#590
b10010110101010110101100000101101 "
b10010110101010110101100000101101 '
b10010110101010110101100000101101 -
b110 !
b110 (
b110 .
b1000 /
b100 3
b101 2
b11 1
b100 0
1#
#595
b1100101 ,
b100110 +
b10100111 *
b10110010 )
b10110010101001110010011001100101 $
b10110010101001110010011001100101 &
#600
0#
#610
b10110010101001110010011001100101 "
b10110010101001110010011001100101 '
b10110010101001110010011001100101 -
b1000 /
b100 3
b101 2
b11 1
b100 0
1#
#615
b1100011 ,
b1100010 +
b11101111 *
b10110001 )
b10110001111011110110001001100011 $
b10110001111011110110001001100011 &
#620
0#
#630
b10110001111011110110001001100011 "
b10110001111011110110001001100011 '
b10110001111011110110001001100011 -
b1000 /
b100 3
b111 2
b11 1
b100 0
1#
#635
b1010 ,
b10000111 +
b1110011 *
b101 )
b101011100111000011100001010 $
b101011100111000011100001010 &
#640
0#
#650
b101011100111000011100001010 "
b101011100111000011100001010 '
b101011100111000011100001010 -
b100 !
b100 (
b100 .
b1000 /
b10 3
b101 2
b100 1
b10 0
1#
#655
b10000000 ,
b100010 +
b111011 *
b11000000 )
b11000000001110110010001010000000 $
b11000000001110110010001010000000 &
#660
0#
#670
b11000000001110110010001010000000 "
b11000000001110110010001010000000 '
b11000000001110110010001010000000 -
b101 !
b101 (
b101 .
b1000 /
b10 3
b101 2
b10 1
b1 0
1#
#675
b100000 ,
b100001 +
b1100100 *
b10000 )
b10000011001000010000100100000 $
b10000011001000010000100100000 &
#680
0#
#690
b10000011001000010000100100000 "
b10000011001000010000100100000 '
b10000011001000010000100100000 -
b1101 !
b1101 (
b1101 .
b1000 /
b1 3
b11 2
b10 1
b1 0
1#
#695
b10101010 ,
b1000101 +
b1111000 *
b1010101 )
b1010101011110000100010110101010 $
b1010101011110000100010110101010 &
#700
0#
#710
b1010101011110000100010110101010 "
b1010101011110000100010110101010 '
b1010101011110000100010110101010 -
b10 !
b10 (
b10 .
b1000 /
b100 3
b100 2
b11 1
b100 0
1#
#715
b10011101 ,
b11001100 +
b11001100 *
b11001110 )
b11001110110011001100110010011101 $
b11001110110011001100110010011101 &
#720
0#
#730
b11001110110011001100110010011101 "
b11001110110011001100110010011101 '
b11001110110011001100110010011101 -
b1001 !
b1001 (
b1001 .
b1000 /
b101 3
b100 2
b100 1
b101 0
1#
#735
b10010110 ,
b111110 +
b100000 *
b11001011 )
b11001011001000000011111010010110 $
b11001011001000000011111010010110 &
#740
0#
#750
b11001011001000000011111010010110 "
b11001011001000000011111010010110 '
b11001011001000000011111010010110 -
b1110 !
b1110 (
b1110 .
b1000 /
b101 3
b1 2
b101 1
b100 0
1#
#755
b10011 ,
b10111000 +
b10000011 *
b10001001 )
b10001001100000111011100000010011 $
b10001001100000111011100000010011 &
#760
0#
#770
b10001001100000111011100000010011 "
b10001001100000111011100000010011 '
b10001001100000111011100000010011 -
b1101 !
b1101 (
b1101 .
b1000 /
b11 3
b11 2
b100 1
b11 0
1#
#775
b1101 ,
b111000 +
b10111100 *
b10000110 )
b10000110101111000011100000001101 $
b10000110101111000011100000001101 &
#780
0#
#790
b10000110101111000011100000001101 "
b10000110101111000011100000001101 '
b10000110101111000011100000001101 -
b1111 !
b1111 (
b1111 .
b1000 /
b11 3
b101 2
b11 1
b11 0
1#
#795
b1010011 ,
b11010110 +
b10100111 *
b10101001 )
b10101001101001111101011001010011 $
b10101001101001111101011001010011 &
#800
0#
#810
b10101001101001111101011001010011 "
b10101001101001111101011001010011 '
b10101001101001111101011001010011 -
b110 !
b110 (
b110 .
b1000 /
b100 3
b101 2
b101 1
b100 0
1#
#815
b1101011 ,
b11011101 +
b10011111 *
b110101 )
b110101100111111101110101101011 $
b110101100111111101110101101011 &
#820
0#
#830
b110101100111111101110101101011 "
b110101100111111101110101101011 '
b110101100111111101110101101011 -
b1 !
b1 (
b1 .
b1000 /
b100 3
b110 2
b110 1
b101 0
1#
#835
b11010101 ,
b101010 +
b10100110 *
b11101010 )
b11101010101001100010101011010101 $
b11101010101001100010101011010101 &
#840
0#
#850
b11101010101001100010101011010101 "
b11101010101001100010101011010101 '
b11101010101001100010101011010101 -
b1011 !
b1011 (
b1011 .
b1000 /
b101 3
b100 2
b11 1
b101 0
1#
#855
b10 ,
b1001010 +
b10111 *
b10000001 )
b10000001000101110100101000000010 $
b10000001000101110100101000000010 &
#860
0#
#870
b10000001000101110100101000000010 "
b10000001000101110100101000000010 '
b10000001000101110100101000000010 -
b11 !
b11 (
b11 .
b1000 /
b10 3
b100 2
b11 1
b1 0
1#
#875
b10101110 ,
b111110 +
b1010110 *
b11010111 )
b11010111010101100011111010101110 $
b11010111010101100011111010101110 &
#880
0#
#890
b11010111010101100011111010101110 "
b11010111010101100011111010101110 '
b11010111010101100011111010101110 -
b1000 /
b110 3
b100 2
b101 1
b101 0
1#
#895
b11101 ,
b11101001 +
b11111111 *
b1110 )
b1110111111111110100100011101 $
b1110111111111110100100011101 &
